aiearth/data/__init__.py
aiearth/data/client.py
aiearth/data/stac_id.py
aiearth/data/loader/__init__.py
aiearth/data/search/__init__.py
aiearth_data-1.0.3.dist-info/METADATA
aiearth_data-1.0.3.dist-info/WHEEL
aiearth_data-1.0.3.dist-info/top_level.txt
aiearth_data-1.0.3.dist-info/RECORD
