Metadata-Version: 2.1
Name: aiearth-data
Version: 1.0.3
Summary: AIEarth Engine Python SDK Data
Home-page: https://engine-aiearth.aliyun.com/
Requires-Python: >=3.8.0
Requires-Dist: aiearth-core (>=1.0.1)
Requires-Dist: numpy (~=1.24.3)
Requires-Dist: oss2 (~=2.18.0)
Requires-Dist: tqdm (~=4.65.0)
Requires-Dist: pyproj (~=3.5.0)
Requires-Dist: matplotlib (~=3.7.1)
Requires-Dist: pystac (~=1.7.3)
Requires-Dist: requests (~=2.31.0)
Requires-Dist: shapely (~=2.0.1)
